torchhandy/Block.py
torchhandy/Conv.py
torchhandy/Diffusion.py
torchhandy/EMA.py
torchhandy/Embedding.py
torchhandy/FC.py
torchhandy/Optimizer.py
torchhandy/Parallel.py
torchhandy/Resize.py
torchhandy/Scheduler.py
torchhandy/Train.py
torchhandy/__init__.py
torchhandy/utils.py
torchhandy-0.1.8.dist-info/METADATA
torchhandy-0.1.8.dist-info/WHEEL
torchhandy-0.1.8.dist-info/licenses/LICENSE
torchhandy-0.1.8.dist-info/RECORD
