Metadata-Version: 2.1
Name: torchhandy
Version: 0.1.8
Summary: torchhandy is a handy package that implements some commonly used modules and function.
Project-URL: Homepage, https://github.com/lleozhang/torchhandy
Author-email: 张荟萱 <pkuleozhang@gmail.com>
License: MIT License
License-File: LICENSE
Classifier: License :: OSI Approved :: MIT License
Classifier: Operating System :: OS Independent
Classifier: Programming Language :: Python :: 3
Requires-Python: >=3.7
Requires-Dist: torch>=2.0.0
